LICENSE
MANIFEST.in
README.md
setup.py
DwaPython.egg-info/PKG-INFO
DwaPython.egg-info/SOURCES.txt
DwaPython.egg-info/dependency_links.txt
DwaPython.egg-info/top_level.txt
dwa/ClassLayer.py
dwa/Dwa.py
dwa/DwaException.py
dwa/Requester.py
dwa/TypeLayer.py
dwa/__init__.py
tests/AllTests.py
tests/ApiTest.py
tests/CharacterTest.py
tests/ClanTest.py
tests/DwaTestCase.py
tests/FactionTest.py
tests/ServerTest.py
tests/UserTest.py
tests/__init__.py